gllm_docproc.cpython-312-x86_64-linux-gnu.so
gllm_docproc.pyi
gllm_docproc/__init__.pyi
gllm_docproc/chunker/__init__.pyi
gllm_docproc/chunker/base_chunker.pyi
gllm_docproc/chunker/structured_element/__init__.pyi
gllm_docproc/chunker/structured_element/chunk_enricher.pyi
gllm_docproc/chunker/structured_element/structured_element_chunker.pyi
gllm_docproc/chunker/table/__init__.pyi
gllm_docproc/chunker/table/table_chunker.pyi
gllm_docproc/converter/__init__.pyi
gllm_docproc/converter/base_converter.pyi
gllm_docproc/data_generator/__init__.pyi
gllm_docproc/data_generator/base_data_generator.pyi
gllm_docproc/data_generator/image_data_generator/__init__.pyi
gllm_docproc/data_generator/image_data_generator/image_caption_data_generator.pyi
gllm_docproc/data_generator/image_data_generator/multi_model_image_caption_data_generator.pyi
gllm_docproc/data_generator/pii_data_generator/__init__.pyi
gllm_docproc/downloader/__init__.pyi
gllm_docproc/downloader/base_downloader.pyi
gllm_docproc/downloader/direct_file_url_downloader.pyi
gllm_docproc/downloader/google_drive_downloader.pyi
gllm_docproc/downloader/html/__init__.pyi
gllm_docproc/downloader/html/firecrawl_downloader.pyi
gllm_docproc/downloader/html/html_downloader.pyi
gllm_docproc/downloader/html/playwright_downloader.pyi
gllm_docproc/downloader/html/requests_downloader.pyi
gllm_docproc/downloader/html/exception/__init__.pyi
gllm_docproc/downloader/html/exception/item_scrape_failed_exception.pyi
gllm_docproc/downloader/html/exception/zyte_api_key_not_provided_exception.pyi
gllm_docproc/downloader/html/scraper/__init__.pyi
gllm_docproc/downloader/html/scraper/web_scraper_executor.pyi
gllm_docproc/downloader/html/scraper/scraper/__init__.pyi
gllm_docproc/downloader/html/scraper/scraper/spiders/__init__.pyi
gllm_docproc/downloader/html/scraper/scraper/spiders/crawl_pdf_spider.pyi
gllm_docproc/downloader/html/scraper/scraper/spiders/crawl_sitemap_link_spider.pyi
gllm_docproc_binary-0.7.25.dist-info/METADATA
gllm_docproc_binary-0.7.25.dist-info/WHEEL
gllm_docproc_binary-0.7.25.dist-info/top_level.txt
gllm_docproc_binary-0.7.25.dist-info/RECORD
